Metadata-Version: 1.0
Name: distributions-BG
Version: 0.1
Summary: Gaussian and Binomial distributions
Home-page: UNKNOWN
Author: Antonio Gonzalez
Author-email: UNKNOWN
License: UNKNOWN
Platform: UNKNOWN
